dsr/__init__.py
dsr/trees.py
dsr-1.0.4.dist-info/LICENSE
dsr-1.0.4.dist-info/METADATA
dsr-1.0.4.dist-info/WHEEL
dsr-1.0.4.dist-info/top_level.txt
dsr-1.0.4.dist-info/RECORD
