Metadata-Version: 2.1
Name: dsr
Version: 1.0.4
Summary: Automatically gegerate repr to show data structures espelly trees
Home-page: https://github.com/the0demiurge/DataStructureRepr
Author: Charles Xu
Author-email: charl3s.xu@gmail.com
License: UNKNOWN
Platform: UNKNOWN
Classifier: Programming Language :: Python
Classifier: License :: Other/Proprietary License
Classifier: Operating System :: Android
Classifier: Operating System :: iOS
Classifier: Operating System :: MacOS
Classifier: Operating System :: Microsoft
Classifier: Operating System :: Other OS
Classifier: Operating System :: POSIX
Classifier: Operating System :: Unix
